{"Plugin Name": "Fieldgroup", "Author": {"dww": {"Profile": {"History": "On Drupal.org for 14 years 3 months", "Languages": ["English", "Portuguese, Brazil", "Spanish"], "Location": "United States", "Profile URL": "https://www.drupal.org/u/dww", "Name": "Derek Wright (dww)"}, "Commit Info": {"Total": "1 commit", "Last": "12 years ago", "First": "12 years ago"}}, "Git Migration": {"Profile": {"History": "On Drupal.org for 9 years 3 months", "Languages": "not found", "Location": "United States", "Profile URL": "https://www.drupal.org/u/git-migration", "Name": "Git Migration"}, "Commit Info": {"Total": "2 commits", "Last": "9 years ago", "First": "9 years ago"}}, "fago": {"Profile": {"History": "On Drupal.org for 15 years 3 months", "Languages": ["English", "German"], "Location": "Vienna", "Profile URL": "https://www.drupal.org/u/fago", "Name": "Wolfgang Ziegler (fago)"}, "Commit Info": {"Total": "18 commits", "Last": "13 years ago", "First": "13 years ago"}}}, "Latest Version": "This project is not covered by Drupal\u2019s security advisory policy.", "Date Modified": "28 March 2017", "Downloads": "851 downloads", "Ratings": "not found", "Sales": "0.00 USD"}